Metadata-Version: 1.0
Name: ku-distributions
Version: 0.1
Summary: Gaussian distributions
Home-page: UNKNOWN
Author: Kishan Udas
Author-email: UNKNOWN
License: UNKNOWN
Platform: UNKNOWN
